MANIFEST.in
README.rst
setup.py
aliyun_python_sdk_rdc.egg-info/PKG-INFO
aliyun_python_sdk_rdc.egg-info/SOURCES.txt
aliyun_python_sdk_rdc.egg-info/dependency_links.txt
aliyun_python_sdk_rdc.egg-info/requires.txt
aliyun_python_sdk_rdc.egg-info/top_level.txt
aliyunsdkrdc/__init__.py
aliyunsdkrdc/endpoint.py
aliyunsdkrdc/request/__init__.py
aliyunsdkrdc/request/v20180816/AddProjectMembersRequest.py
aliyunsdkrdc/request/v20180816/CreateProjectRequest.py
aliyunsdkrdc/request/v20180816/DeleteProjectMembersRequest.py
aliyunsdkrdc/request/v20180816/GetProjectInfoRequest.py
aliyunsdkrdc/request/v20180816/UpdateProjectRequest.py
aliyunsdkrdc/request/v20180816/__init__.py
aliyunsdkrdc/request/v20180821/AddEnterpriseMemberRequest.py
aliyunsdkrdc/request/v20180821/AddRamMemberRequest.py
aliyunsdkrdc/request/v20180821/ApproveJoinCompanyRequest.py
aliyunsdkrdc/request/v20180821/CreateEnterpriseRequest.py
aliyunsdkrdc/request/v20180821/CreateWorkitemRequest.py
aliyunsdkrdc/request/v20180821/GetBindedUserByDingIdRequest.py
aliyunsdkrdc/request/v20180821/GetChangeLogRequest.py
aliyunsdkrdc/request/v20180821/GetCustomFieldsByTemplateIdRequest.py
aliyunsdkrdc/request/v20180821/GetIssueByIdRequest.py
aliyunsdkrdc/request/v20180821/GetJoinCodeRequest.py
aliyunsdkrdc/request/v20180821/GetProjectMembersRequest.py
aliyunsdkrdc/request/v20180821/GetUserByAliyunPkRequest.py
aliyunsdkrdc/request/v20180821/GetWorkitemByIdRequest.py
aliyunsdkrdc/request/v20180821/JoinCompanyRequest.py
aliyunsdkrdc/request/v20180821/SearchProjectsByRegionRequest.py
aliyunsdkrdc/request/v20180821/SearchTestCaseRequest.py
aliyunsdkrdc/request/v20180821/SearchWorkitemRequest.py
aliyunsdkrdc/request/v20180821/SearchWorkitemWithTotalCountRequest.py
aliyunsdkrdc/request/v20180821/SyncUserToRdcRequest.py
aliyunsdkrdc/request/v20180821/UpdateWorkitemRequest.py
aliyunsdkrdc/request/v20180821/__init__.py